README.md
setup.py
bin/de_sequencer
design_explorer/__init__.py
design_explorer/graph.py
design_explorer/sequencer.py
design_explorer/utils.py
design_explorer.egg-info/PKG-INFO
design_explorer.egg-info/SOURCES.txt
design_explorer.egg-info/dependency_links.txt
design_explorer.egg-info/not-zip-safe
design_explorer.egg-info/top_level.txt
design_explorer/tests/__init__.py
design_explorer/tests/test_graph.py
design_explorer/tests/test_sequencer.py
design_explorer/tests/de_sequencer/__init__.py
design_explorer/tests/de_sequencer/test_de_sequencer.py
design_explorer/tests/de_sequencer/test_hierarchy.py