Metadata-Version: 1.1
Name: design-explorer
Version: 0.3
Summary: Design Explorer
Home-page: https://github.com/jeremiah-c-leary/design-explorer
Author: Jeremiah C Leary
Author-email: jeremiah.c.leary@gmail.com
License: GNU General Public License
Download-URL: https://github.com/jeremiah-c-leary/design-explorer
Keywords: vhdl,verilog
Platform: UNKNOWN
Classifier: Development Status :: 2 - Pre-Alpha
Classifier: Environment :: Console
Classifier: Programming Language :: Python :: 2.7
Classifier: Intended Audience :: End Users/Desktop
Classifier: License :: OSI Approved :: GNU General Public License v3 (GPLv3)
Classifier: Natural Language :: English
Classifier: Operating System :: POSIX :: Linux
Classifier: Topic :: Text Processing :: General
